belvo/__init__.py
belvo/client.py
belvo/core/__init__.py
belvo/core/api_error.py
belvo/core/datetime_utils.py
belvo/core/jsonable_encoder.py
belvo/core/remove_none_from_headers.py
belvo/environment.py
belvo/errors/__init__.py
belvo/errors/bad_request_error.py
belvo/errors/forbidden_error.py
belvo/errors/internal_server_error.py
belvo/errors/not_found_error.py
belvo/errors/precondition_error.py
belvo/errors/request_timeout_error.py
belvo/errors/unauthorized_error.py
belvo/py.typed
belvo/resources/__init__.py
belvo/resources/accounts/__init__.py
belvo/resources/accounts/client.py
belvo/resources/balances/__init__.py
belvo/resources/balances/client.py
belvo/resources/bank_accounts/__init__.py
belvo/resources/bank_accounts/client.py
belvo/resources/categorization/__init__.py
belvo/resources/categorization/client.py
belvo/resources/customers/__init__.py
belvo/resources/customers/client.py
belvo/resources/employment_records/__init__.py
belvo/resources/employment_records/client.py
belvo/resources/income_verification/__init__.py
belvo/resources/income_verification/client.py
belvo/resources/incomes/__init__.py
belvo/resources/incomes/client.py
belvo/resources/institutions/__init__.py
belvo/resources/institutions/client.py
belvo/resources/investment_portfolios/__init__.py
belvo/resources/investment_portfolios/client.py
belvo/resources/invoices/__init__.py
belvo/resources/invoices/client.py
belvo/resources/links/__init__.py
belvo/resources/links/client.py
belvo/resources/owners/__init__.py
belvo/resources/owners/client.py
belvo/resources/payment_institutions/__init__.py
belvo/resources/payment_institutions/client.py
belvo/resources/payment_intents/__init__.py
belvo/resources/payment_intents/client.py
belvo/resources/payment_links/__init__.py
belvo/resources/payment_links/client.py
belvo/resources/payment_transactions/__init__.py
belvo/resources/payment_transactions/client.py
belvo/resources/payment_webhooks/__init__.py
belvo/resources/payment_webhooks/client.py
fern_belvo-0.0.34.dist-info/METADATA
fern_belvo-0.0.34.dist-info/WHEEL
fern_belvo-0.0.34.dist-info/RECORD
